madhatter/__init__.py
madhatter/__main__.py
madhatter/benchmark.py
madhatter/loaders.py
madhatter/metrics.py
madhatter/models.py
madhatter/utils.py
madhatter-0.0.1.dist-info/LICENSE
madhatter-0.0.1.dist-info/METADATA
madhatter-0.0.1.dist-info/WHEEL
madhatter-0.0.1.dist-info/top_level.txt
madhatter-0.0.1.dist-info/RECORD
