Metadata-Version: 2.1
Name: madhatter
Version: 0.0.1
Summary: A text benchmarking tool for writers and data scientists alike.
Author-email: Matey Krastev <matey.krastev@outlook.com>
Project-URL: Homepage, https://github.com/Rinto-kun/madhatter
Project-URL: Bug Tracker, https://github.com/Rinto-kun/madhatter/issues
Classifier: Programming Language :: Python :: 3
Classifier: License :: OSI Approved :: MIT License
Classifier: Operating System :: OS Independent
Requires-Python: >=3.7
License-File: LICENSE
Requires-Dist: numpy
Requires-Dist: matplotlib
Requires-Dist: nltk
Requires-Dist: requests
Requires-Dist: pandas
Requires-Dist: seaborn
Requires-Dist: scikit-learn
Requires-Dist: tqdm
Requires-Dist: torch
Requires-Dist: transformers
Requires-Dist: gensim
